x_robots_tag_middleware/__init__.py
x_robots_tag_middleware/apps.py
x_robots_tag_middleware/middleware.py
x_robots_tag_middleware/tests.py
django_x_robots_tag_middleware-1.3.3.dist-info/LICENSE
django_x_robots_tag_middleware-1.3.3.dist-info/METADATA
django_x_robots_tag_middleware-1.3.3.dist-info/WHEEL
django_x_robots_tag_middleware-1.3.3.dist-info/top_level.txt
django_x_robots_tag_middleware-1.3.3.dist-info/RECORD
