Metadata-Version: 2.1
Name: django-x-robots-tag-middleware
Version: 1.3.3
Summary: Enables returning the X-Robots-Tag header based on Django settings.
Home-page: https://github.com/cyface/django-x-robots-tag-middleware
Author: Tim White
Author-email: tim@cyface.com
License: MIT
Platform: UNKNOWN
Classifier: Development Status :: 5 - Production/Stable
Classifier: Framework :: Django
Classifier: Intended Audience :: Developers
Classifier: License :: OSI Approved :: MIT License
Classifier: Operating System :: OS Independent
Classifier: Programming Language :: Python :: 3.6
Classifier: Programming Language :: Python :: 3.7
Classifier: Programming Language :: Python :: 3.8
Classifier: Topic :: Internet :: WWW/HTTP
Requires-Dist: django (>=1.10)
